{"data":"2026-07-04","snapshots":[{"ts":"2026-07-04T08:54:06","ibov_spot":175000,"convergencias":[{"strike_win":175100,"score":8.9,"n_pilares":2,"pilares":["SPY","VALE"],"direction":"BEAR","consensus":0.3,"has_divergence":true,"opt":"Call","vol_total":149191.0,"fin_total":32158610.0},{"strike_win":174600,"score":4.45,"n_pilares":2,"pilares":["EEM","SPY"],"direction":"BULL","consensus":0.52,"has_divergence":true,"opt":"Call","vol_total":123711.0,"fin_total":29639238.5}]},{"ts":"2026-07-04T14:04:38","ibov_spot":177620,"convergencias":[{"strike_win":177700,"score":8.9,"n_pilares":2,"pilares":["SPY","VALE"],"direction":"BEAR","consensus":0.3,"has_divergence":true,"opt":"Call","vol_total":149191.0,"fin_total":32158610.0}]},{"ts":"2026-07-04T14:05:02","ibov_spot":177620,"convergencias":[{"strike_win":177700,"score":8.9,"n_pilares":2,"pilares":["SPY","VALE"],"direction":"BEAR","consensus":0.3,"has_divergence":true,"opt":"Call","vol_total":149191.0,"fin_total":32158610.0}]},{"ts":"2026-07-04T14:05:13","ibov_spot":177620,"convergencias":[{"strike_win":177700,"score":8.9,"n_pilares":2,"pilares":["SPY","VALE"],"direction":"BEAR","consensus":0.3,"has_divergence":true,"opt":"Call","vol_total":149191.0,"fin_total":32158610.0}]},{"ts":"2026-07-04T14:56:01","ibov_spot":176720,"convergencias":[{"strike_win":176800,"score":8.9,"n_pilares":2,"pilares":["SPY","VALE"],"direction":"BEAR","consensus":0.3,"has_divergence":true,"opt":"Call","vol_total":149191.0,"fin_total":32158610.0}]},{"ts":"2026-07-04T15:07:39","ibov_spot":174200,"convergencias":[{"strike_win":174300,"score":8.9,"n_pilares":2,"pilares":["SPY","VALE"],"direction":"BEAR","consensus":0.3,"has_divergence":true,"opt":"Call","vol_total":149191.0,"fin_total":32158610.0},{"strike_win":173800,"score":4.45,"n_pilares":2,"pilares":["EEM","SPY"],"direction":"BULL","consensus":0.52,"has_divergence":true,"opt":"Call","vol_total":123711.0,"fin_total":29639238.5}]},{"ts":"2026-07-04T15:09:00","ibov_spot":174200,"convergencias":[{"strike_win":174300,"score":8.9,"n_pilares":2,"pilares":["SPY","VALE"],"direction":"BEAR","consensus":0.3,"has_divergence":true,"opt":"Call","vol_total":149191.0,"fin_total":32158610.0},{"strike_win":173800,"score":4.45,"n_pilares":2,"pilares":["EEM","SPY"],"direction":"BULL","consensus":0.52,"has_divergence":true,"opt":"Call","vol_total":123711.0,"fin_total":29639238.5}]},{"ts":"2026-07-04T15:13:30","ibov_spot":174200,"convergencias":[{"strike_win":174300,"score":8.9,"n_pilares":2,"pilares":["SPY","VALE"],"direction":"BEAR","consensus":0.3,"has_divergence":true,"opt":"Call","vol_total":149191.0,"fin_total":32158610.0},{"strike_win":173800,"score":4.45,"n_pilares":2,"pilares":["EEM","SPY"],"direction":"BULL","consensus":0.52,"has_divergence":true,"opt":"Call","vol_total":123711.0,"fin_total":29639238.5}]},{"ts":"2026-07-04T15:14:07","ibov_spot":174200,"convergencias":[{"strike_win":174300,"score":8.9,"n_pilares":2,"pilares":["SPY","VALE"],"direction":"BEAR","consensus":0.3,"has_divergence":true,"opt":"Call","vol_total":149191.0,"fin_total":32158610.0},{"strike_win":173800,"score":4.45,"n_pilares":2,"pilares":["EEM","SPY"],"direction":"BULL","consensus":0.52,"has_divergence":true,"opt":"Call","vol_total":123711.0,"fin_total":29639238.5}]},{"ts":"2026-07-04T15:20:33","ibov_spot":176700,"convergencias":[{"strike_win":176800,"score":8.9,"n_pilares":2,"pilares":["SPY","VALE"],"direction":"BEAR","consensus":0.3,"has_divergence":true,"opt":"Call","vol_total":149191.0,"fin_total":32158610.0},{"strike_win":176300,"score":4.45,"n_pilares":2,"pilares":["EEM","SPY"],"direction":"BULL","consensus":0.52,"has_divergence":true,"opt":"Call","vol_total":123711.0,"fin_total":29639238.5}]},{"ts":"2026-07-04T15:29:07","ibov_spot":176700,"convergencias":[{"strike_win":176800,"score":8.9,"n_pilares":2,"pilares":["SPY","VALE"],"direction":"BEAR","consensus":0.3,"has_divergence":true,"opt":"Call","vol_total":149191.0,"fin_total":32158610.0},{"strike_win":176300,"score":4.45,"n_pilares":2,"pilares":["EEM","SPY"],"direction":"BULL","consensus":0.52,"has_divergence":true,"opt":"Call","vol_total":123711.0,"fin_total":29639238.5}]},{"ts":"2026-07-04T15:33:07","ibov_spot":176700,"convergencias":[{"strike_win":176800,"score":8.9,"n_pilares":2,"pilares":["SPY","VALE"],"direction":"BEAR","consensus":0.3,"has_divergence":true,"opt":"Call","vol_total":149191.0,"fin_total":32158610.0},{"strike_win":176300,"score":4.45,"n_pilares":2,"pilares":["EEM","SPY"],"direction":"BULL","consensus":0.52,"has_divergence":true,"opt":"Call","vol_total":123711.0,"fin_total":29639238.5}]},{"ts":"2026-07-04T15:40:54","ibov_spot":176700,"convergencias":[{"strike_win":176800,"score":8.9,"n_pilares":2,"pilares":["SPY","VALE"],"direction":"BEAR","consensus":0.3,"has_divergence":true,"opt":"Call","vol_total":149191.0,"fin_total":32158610.0},{"strike_win":176300,"score":4.45,"n_pilares":2,"pilares":["EEM","SPY"],"direction":"BULL","consensus":0.52,"has_divergence":true,"opt":"Call","vol_total":123711.0,"fin_total":29639238.5}]},{"ts":"2026-07-04T15:47:03","ibov_spot":176700,"convergencias":[{"strike_win":176800,"score":8.9,"n_pilares":2,"pilares":["SPY","VALE"],"direction":"BEAR","consensus":0.3,"has_divergence":true,"opt":"Call","vol_total":149191.0,"fin_total":32158610.0},{"strike_win":176300,"score":4.45,"n_pilares":2,"pilares":["EEM","SPY"],"direction":"BULL","consensus":0.52,"has_divergence":true,"opt":"Call","vol_total":123711.0,"fin_total":29639238.5}]},{"ts":"2026-07-04T15:50:52","ibov_spot":176700,"convergencias":[{"strike_win":176800,"score":8.9,"n_pilares":2,"pilares":["SPY","VALE"],"direction":"BEAR","consensus":0.3,"has_divergence":true,"opt":"Call","vol_total":149191.0,"fin_total":32158610.0},{"strike_win":176300,"score":4.45,"n_pilares":2,"pilares":["EEM","SPY"],"direction":"BULL","consensus":0.52,"has_divergence":true,"opt":"Call","vol_total":123711.0,"fin_total":29639238.5}]},{"ts":"2026-07-04T15:51:10","ibov_spot":176700,"convergencias":[{"strike_win":176800,"score":8.9,"n_pilares":2,"pilares":["SPY","VALE"],"direction":"BEAR","consensus":0.3,"has_divergence":true,"opt":"Call","vol_total":149191.0,"fin_total":32158610.0},{"strike_win":176300,"score":4.45,"n_pilares":2,"pilares":["EEM","SPY"],"direction":"BULL","consensus":0.52,"has_divergence":true,"opt":"Call","vol_total":123711.0,"fin_total":29639238.5}]}]}